napari_animated_gif_io/__init__.py
napari_animated_gif_io/_function.py
napari_animated_gif_io/_writer.py
napari_animated_gif_io/_tests/__init__.py
napari_animated_gif_io/_tests/test_function.py
napari_animated_gif_io/_tests/test_writer.py
napari_animated_gif_io-0.1.2.dist-info/LICENSE
napari_animated_gif_io-0.1.2.dist-info/METADATA
napari_animated_gif_io-0.1.2.dist-info/WHEEL
napari_animated_gif_io-0.1.2.dist-info/entry_points.txt
napari_animated_gif_io-0.1.2.dist-info/top_level.txt
napari_animated_gif_io-0.1.2.dist-info/RECORD
